MANIFEST.in
README.md
requirements.txt
setup.py
formcreator/__init__.py
formcreator/models.py
formcreator.egg-info/PKG-INFO
formcreator.egg-info/SOURCES.txt
formcreator.egg-info/dependency_links.txt
formcreator.egg-info/not-zip-safe
formcreator.egg-info/requires.txt
formcreator.egg-info/top_level.txt
formcreator/blocks/__init__.py
formcreator/fields/__init__.py
formcreator/static/.gitignore
formcreator/static/.htaccess
formcreator/static/README.rst
formcreator/static/apple-touch-icon-114x114-precomposed.png
formcreator/static/apple-touch-icon-57x57-precomposed.png
formcreator/static/apple-touch-icon-72x72-precomposed.png
formcreator/static/apple-touch-icon-precomposed.png
formcreator/static/apple-touch-icon.png
formcreator/static/crossdomain.xml
formcreator/static/favicon.ico
formcreator/static/humans.txt
formcreator/static/robots.txt
formcreator/static/coffee/script.coffee
formcreator/static/css/bootstrap-responsive.min.css
formcreator/static/css/bootstrap.min.css
formcreator/static/css/inner.css
formcreator/static/css/outer.css
formcreator/static/css/style.css
formcreator/static/img/.gitignore
formcreator/static/img/glyphicons-halflings-white.png
formcreator/static/img/glyphicons-halflings.png
formcreator/static/js/plugins.js
formcreator/static/js/script.js
formcreator/static/js/libs/bootstrap.min.js
formcreator/static/js/libs/jquery.min.js
formcreator/static/js/libs/modernizr-2.0.6.min.js
formcreator/static/test/index.html
formcreator/static/test/tests.js
formcreator/static/test/qunit/qunit.css
formcreator/static/test/qunit/qunit.js
formcreator/templates/404.html
formcreator/templates/base.html
formcreator/templates/dir_contents.html
formcreator/templates/form.html
formcreator/templates/home.html
formcreator/templates/index.html
formcreator/templates/inner_base.html
formcreator/templates/login.html
formcreator/templates/logout.html
formcreator/templates/select_files.html
formcreator/templates/user_create.html