Metadata-Version: 1.0
Name: formcreator
Version: 0.1.2
Summary: Create web forms for command line programs or python functions
Home-page: http://github.com/aivuk/formcreator
Author: Edgar Z. Alvarenga
Author-email: e@vaz.io
License: BSD 2-Clause
Platform: UNKNOWN
